pylatex_sssi111/__init__.py
pylatex_sssi111/latex_generator.py
pylatex_sssi111-0.1.3.dist-info/METADATA
pylatex_sssi111-0.1.3.dist-info/WHEEL
pylatex_sssi111-0.1.3.dist-info/RECORD
