Metadata-Version: 2.1
Name: pylatex_sssi111
Version: 0.1.3
Summary: LaTeX document generator
Author: sssi111
Author-email: truesssi111@gmail.com
Requires-Python: >=3.8,<4.0
Classifier: Programming Language :: Python :: 3
Classifier: Programming Language :: Python :: 3.8
Classifier: Programming Language :: Python :: 3.9
Classifier: Programming Language :: Python :: 3.10
Classifier: Programming Language :: Python :: 3.11
Classifier: Programming Language :: Python :: 3.12
